{
  "user_id": "AHOREIE3MS6AB3GZJMIY7TEYB5GA",
  "candidate_list": [
    "B081JQV816",
    "B00KXGZYBG",
    "B08NCGN9K6",
    "B01CQAGNSO",
    "B00000K2XJ",
    "B087T3N8WB",
    "B08T2M787L",
    "B0BN9ZCLGB",
    "B015A3DT2W",
    "B0BGQ6VKC6",
    "B01JQDLZ3W",
    "B01EYEUU8Y",
    "B07SDCJD8P",
    "B09FTYNVMP",
    "B000ZLOGCC",
    "B00QGAU5V2",
    "B000Q6ZLH0",
    "B001XJBWXG",
    "B01J4K6ZB4",
    "B087NNPYP3"
  ],
  "candidate_category": "Video Games",
  "source": "amazon",
  "type": "recommendation",
  "loc": [
    -1,
    -1
  ]
}