{
  "user_id": "AEICUFY2URPXDOWDADSDOZMTAZ6A",
  "candidate_list": [
    "B08P1TS5YN",
    "B01DLIJOAO",
    "B002Q0WSO8",
    "B001QCWRZW",
    "B0BZJ6B836",
    "B0B3DZNFWX",
    "B000OLSJLC",
    "B0BRG26SYG",
    "B0002DVCB6",
    "B07982R9BZ",
    "B0B5FFXM61",
    "B07K1VXCDR",
    "B089XYZPT9",
    "B09VJFNC98",
    "B08WBB1MKX",
    "B00P8ZBRE0",
    "B07PJVWKBP",
    "B09BS25NJM",
    "B0B1MCJBQF",
    "B09ZLLWWKD"
  ],
  "candidate_category": "Musical Instruments",
  "source": "amazon",
  "type": "recommendation",
  "loc": [
    -1,
    -1
  ]
}