{
  "user_id": "AHBZZHJSXR2Y7SXFZ6FDOEQ5FFNA",
  "candidate_list": [
    "B0B2VWZGZ4",
    "B07W6PYNS5",
    "B001C00DA4",
    "B001GF9AS6",
    "B001ELJFFU",
    "B09SFS3TFT",
    "B001HL3Q70",
    "B07592GDN6",
    "B001ELJFBE",
    "B0BKZ5JSVF",
    "B07P11GJMG",
    "B007RW6UWQ",
    "B0049B3G1Q",
    "B0BTHGL693",
    "B0BHSG5C3G",
    "B09XDRJSSR",
    "B01I4ZQU88",
    "B00B7MVV44",
    "B073X4V4V4",
    "B09M8CVL3L"
  ],
  "candidate_category": "Industrial & Scientific",
  "source": "amazon",
  "type": "recommendation",
  "loc": [
    -1,
    -1
  ]
}