{
  "user_id": "AGLRJEPVTZUWEZ7O2B75424ZQ7VA",
  "candidate_list": [
    "B07MH217YP",
    "B00NWGZ4XC",
    "B08LGH7MLQ",
    "B08LH276DH",
    "B0BY555D8V",
    "B00VUXD7ZG",
    "B0833SSMPC",
    "B07TS649XB",
    "B09TX2TX7S",
    "B008TNAGQS",
    "B0C3VMWDLL",
    "B008MG3EFM",
    "B00162VVN6",
    "B00GXM48HA",
    "B006VE454Q",
    "B07FLTG5LK",
    "B07H4JB487",
    "B0BBGC9FXZ",
    "B0BPH84SR1",
    "B0044DE8A2"
  ],
  "candidate_category": "Industrial & Scientific",
  "source": "amazon",
  "type": "recommendation",
  "loc": [
    -1,
    -1
  ]
}