{
  "user_id": "AHKEHAX7U7HUXZCHG5GBNJTROLTQ",
  "candidate_list": [
    "B091NZ1WHC",
    "B093DDT85Y",
    "B078JPPT3N",
    "B001F85SSU",
    "B0B28BBSHJ",
    "B000086JYJ",
    "B008GFZV6Y",
    "B0718VWCB9",
    "B00M6SJ3CU",
    "B0002D0PWI",
    "B0BZD63R13",
    "B089XVHGGT",
    "B00KJ7UP04",
    "B0BTHHN5ZK",
    "B01NAEX3YB",
    "B0BKZ1GPM7",
    "B0BZRD34C2",
    "B003RRTX38",
    "B00006JC46",
    "B018SLIVOE"
  ],
  "candidate_category": "Musical Instruments",
  "source": "amazon",
  "type": "recommendation",
  "loc": [
    -1,
    -1
  ]
}