{
  "user_id": "AHPYSVIL4FIXZLVK5YGMZNDEXP5Q",
  "candidate_list": [
    "B0C4S6PJ25",
    "B00004YOIV",
    "B06XRC711R",
    "B09BBMJXMB",
    "B0032A8SLS",
    "B0BZHVJWBP",
    "B0B2495HYX",
    "B07G61G6MG",
    "B0994PTMR1",
    "B00002EPZ2",
    "B00IRLHE8A",
    "B00DJRLDMU",
    "B000035XYT",
    "B072N5544R",
    "B01JS3F7AW",
    "B07RBMZRP3",
    "B01LYRKW83",
    "B09YDBKT7M",
    "B000ETJJAE",
    "B091F1HPCW"
  ],
  "candidate_category": "Video Games",
  "source": "amazon",
  "type": "recommendation",
  "loc": [
    -1,
    -1
  ]
}