{
  "user_id": "AGNY4X776V2MSQOLUQZDKOOFZSSA",
  "candidate_list": [
    "B07G5XWQ6B",
    "B00AHKXPFA",
    "B0BLCXFCY7",
    "B000ZK695U",
    "B09PG3HQ5L",
    "B09KKJFZ82",
    "B000077WZP",
    "B00004YYD2",
    "B0007SKSFC",
    "B00097CZ5W",
    "B0C9J9MNJM",
    "B072NZBSXK",
    "B0050SYYEK",
    "B0080JP4M2",
    "B00F9FPWYU",
    "B06WW86T94",
    "B07D58WSDB",
    "B083DKN9SC",
    "B000069BCW",
    "B07C9FBHKR"
  ],
  "candidate_category": "Computers",
  "source": "amazon",
  "type": "recommendation",
  "loc": [
    -1,
    -1
  ]
}