{
  "user_id": "AFQ2CWMMW3TOIRSYRL7NQKSZ33EQ",
  "candidate_list": [
    "B076Q5V788",
    "B07GC2YSBG",
    "B0749RXGB4",
    "B0723F4FD4",
    "B0002WYUAW",
    "B0BKZ1KXLM",
    "B004DERANY",
    "B08V3B7X78",
    "B00GFF5YXM",
    "B01MRXNEFW",
    "B083V5XYX8",
    "B0050Q03U6",
    "B0BLMP94R9",
    "B00TV90MT0",
    "B0BBWK1XWT",
    "B0764F75C8",
    "B07P3MFG5D",
    "B00163ROMW",
    "B000A0IBLK",
    "B015VRDCJ2"
  ],
  "candidate_category": "Industrial & Scientific",
  "source": "amazon",
  "type": "recommendation",
  "loc": [
    -1,
    -1
  ]
}