{
  "user_id": "AETQSA37UQQWEROYBWLZ5QNXNI5Q",
  "candidate_list": [
    "B09RHNXJMW",
    "B089SWNVTZ",
    "B0BBRG15WL",
    "B0070TWXN6",
    "B007NAGE96",
    "B0C53QBNQQ",
    "B07CC9K599",
    "B081FKL957",
    "B0BGP84KMF",
    "B005JX5IUK",
    "B08HRTWG2R",
    "B088FPNVVF",
    "B0B4JY92NM",
    "B08VS74MJ6",
    "B087DYKJ1C",
    "B09JZRCJJV",
    "B0BRK5XNBK",
    "B07CLZMCYK",
    "B0B4NMYTT3",
    "B07GF3XL83"
  ],
  "candidate_category": "Musical Instruments",
  "source": "amazon",
  "type": "recommendation",
  "loc": [
    -1,
    -1
  ]
}