{
  "user_id": "AETQWA3UV3XG4BZKL3VP7CTTZPCQ",
  "candidate_list": [
    "B07GYBBW7W",
    "B09B45DLQG",
    "B09G6GGB9R",
    "B0147DEV2I",
    "B00004SVND",
    "B07ZV8DG9T",
    "B095K9T8QH",
    "B07G34RPZR",
    "B00MPHYCQ4",
    "B0026FCKTG",
    "B075MT363Z",
    "B07N2VR5MH",
    "B003P15MTK",
    "B0000A344M",
    "B002SRPAAS",
    "B000095ZH4",
    "B085BWDT68",
    "B00F27JGVA",
    "B0865RFFMH",
    "B01MFFGRVP"
  ],
  "candidate_category": "Musical Instruments",
  "source": "amazon",
  "type": "recommendation",
  "loc": [
    -1,
    -1
  ]
}