{
  "user_id": "dca7ab0c20838e0598f8a563d1a4f8ad",
  "candidate_list": [
    "6131869",
    "1460685",
    "21957767",
    "1544862",
    "3436296",
    "1669205",
    "20738195",
    "851079",
    "28687021",
    "32282928",
    "1186366",
    "294971",
    "1116004",
    "11635762",
    "17406188",
    "25889454",
    "24688",
    "1104398",
    "1228936",
    "25715797"
  ],
  "candidate_category": "book - to-read",
  "source": "goodreads",
  "type": "recommendation",
  "loc": [
    -1,
    -1
  ]
}