{
  "user_id": "43fc519e5ecc87e8f0451813faf1611f",
  "candidate_list": [
    "23823722",
    "4778650",
    "22609571",
    "354465",
    "1121202",
    "30087933",
    "61049",
    "13507173",
    "1311344",
    "6439013",
    "11179074",
    "7372927",
    "5722939",
    "13723892",
    "4762745",
    "2871820",
    "20613613",
    "17267038",
    "8099521",
    "12257611"
  ],
  "candidate_category": "book - to-read",
  "source": "goodreads",
  "type": "recommendation",
  "loc": [
    -1,
    -1
  ]
}