{
  "user_id": "30d77337dd55268eea4fde9f698d3c52",
  "candidate_list": [
    "18049625",
    "806158",
    "8815327",
    "6440532",
    "22464463",
    "1493616",
    "4853676",
    "18397872",
    "12908687",
    "418884",
    "979018",
    "30287217",
    "13260647",
    "30328530",
    "9179493",
    "18274899",
    "25557784",
    "18232122",
    "2099166",
    "207917"
  ],
  "candidate_category": "book - to-read",
  "source": "goodreads",
  "type": "recommendation",
  "loc": [
    -1,
    -1
  ]
}