{
  "user_id": "e9da2b953466eb3ed6dc5d89f53b826e",
  "candidate_list": [
    "6655",
    "902883",
    "349461",
    "6068932",
    "28561621",
    "13541026",
    "23316805",
    "1406310",
    "2829893",
    "15798751",
    "10071",
    "28695330",
    "1604243",
    "24104845",
    "12340317",
    "15801313",
    "28251384",
    "327351",
    "13101266",
    "3758769"
  ],
  "candidate_category": "book - classics",
  "source": "goodreads",
  "type": "recommendation",
  "loc": [
    -1,
    -1
  ]
}