{
  "user_id": "3c2d8bcb37949a3128aeb10eb85f6001",
  "candidate_list": [
    "34388342",
    "35264578",
    "20556968",
    "904585",
    "3182650",
    "1394796",
    "27802791",
    "10639052",
    "1645615",
    "409967",
    "1963941",
    "20638702",
    "8411679",
    "35530158",
    "583065",
    "828407",
    "25663504",
    "37983",
    "296866",
    "453415"
  ],
  "candidate_category": "book - to-read",
  "source": "goodreads",
  "type": "recommendation",
  "loc": [
    -1,
    -1
  ]
}