{
  "user_id": "68118d13a6e6f38f255435e455072e74",
  "candidate_list": [
    "30749842",
    "372359",
    "13384490",
    "12556680",
    "448092",
    "31423329",
    "14841576",
    "31565803",
    "5354780",
    "102606",
    "28695418",
    "2956411",
    "1829059",
    "13038985",
    "12369392",
    "999984",
    "6985459",
    "22887973",
    "18336230",
    "1012314"
  ],
  "candidate_category": "book - to-read",
  "source": "goodreads",
  "type": "recommendation",
  "loc": [
    -1,
    -1
  ]
}