{
  "user_id": "f4e767e1894922a13ca245084431c81e",
  "candidate_list": [
    "18690641",
    "603630",
    "13790750",
    "7632758",
    "25532006",
    "2841732",
    "25311290",
    "36335157",
    "23167738",
    "22669385",
    "26202698",
    "13067526",
    "366970",
    "4215733",
    "1290693",
    "1024901",
    "18407009",
    "33547104",
    "1258941",
    "985596"
  ],
  "candidate_category": "book - to-read",
  "source": "goodreads",
  "type": "recommendation",
  "loc": [
    -1,
    -1
  ]
}