{
  "user_id": "894ea5a7d81b8c3e1546a19d6540eeda",
  "candidate_list": [
    "17617148",
    "15836600",
    "409204",
    "630614",
    "9821523",
    "1859739",
    "20488612",
    "355591",
    "27224184",
    "5",
    "111895",
    "6452516",
    "9705176",
    "2698953",
    "476899",
    "24484455",
    "29324604",
    "6965298",
    "27154693",
    "1014090"
  ],
  "candidate_category": "book - favorites",
  "source": "goodreads",
  "type": "recommendation",
  "loc": [
    -1,
    -1
  ]
}