{
  "user_id": "3ca02e9928d677326eb3ff080b56f1bb",
  "candidate_list": [
    "2192964",
    "21488431",
    "18480112",
    "12431948",
    "3321597",
    "23754",
    "3301072",
    "444661",
    "30821436",
    "8505298",
    "8634810",
    "22808342",
    "21472060",
    "4339836",
    "1141446",
    "412286",
    "11951697",
    "811353",
    "17191715",
    "20367603"
  ],
  "candidate_category": "book - to-read",
  "source": "goodreads",
  "type": "recommendation",
  "loc": [
    -1,
    -1
  ]
}