{
  "user_id": "9399906e14983a2f081f71215b94bf4a",
  "candidate_list": [
    "1945606",
    "29987263",
    "18246115",
    "15196",
    "15760551",
    "6392365",
    "19666097",
    "27826",
    "1693472",
    "18383675",
    "6425120",
    "16133115",
    "2283389",
    "222804",
    "25539337",
    "2009586",
    "18891355",
    "24971789",
    "6889271",
    "7134639"
  ],
  "candidate_category": "book - to-read",
  "source": "goodreads",
  "type": "recommendation",
  "loc": [
    -1,
    -1
  ]
}