{
  "user_id": "8fbab081b6d44a3a1ab4a83a80126dd6",
  "candidate_list": [
    "868591",
    "28593071",
    "79545",
    "16290041",
    "6314857",
    "237063",
    "33897637",
    "21454033",
    "19901327",
    "18300840",
    "6477991",
    "27844101",
    "20320100",
    "11607446",
    "33965636",
    "34328726",
    "537886",
    "36390749",
    "6271186",
    "44735"
  ],
  "candidate_category": "book - to-read",
  "source": "goodreads",
  "type": "recommendation",
  "loc": [
    -1,
    -1
  ]
}