{
  "user_id": "32e14b8db349934d06bb9fe657b4b79b",
  "candidate_list": [
    "1808067",
    "2976868",
    "853707",
    "11548444",
    "9656006",
    "2359401",
    "1079834",
    "25470358",
    "30075802",
    "15788807",
    "36148470",
    "2876756",
    "15742911",
    "907727",
    "26157301",
    "6004166",
    "18515732",
    "22744317",
    "18163527",
    "27250531"
  ],
  "candidate_category": "book - to-read",
  "source": "goodreads",
  "type": "recommendation",
  "loc": [
    -1,
    -1
  ]
}