{
  "user_id": "64da63a87d510dd85a3580953c938718",
  "candidate_list": [
    "1293956",
    "570274",
    "30119",
    "237665",
    "1816735",
    "15791672",
    "959566",
    "24872400",
    "17612066",
    "7011179",
    "1924956",
    "29332505",
    "16032840",
    "18130375",
    "34051393",
    "18051312",
    "15708164",
    "1105004",
    "8535824",
    "22706843"
  ],
  "candidate_category": "book - to-read",
  "source": "goodreads",
  "type": "recommendation",
  "loc": [
    -1,
    -1
  ]
}