{
  "user_id": "3f043aad908c50f9edbead16fad2517b",
  "candidate_list": [
    "6786725",
    "2408158",
    "25023476",
    "231850",
    "7707210",
    "26073118",
    "2340255",
    "17672845",
    "34211152",
    "9974879",
    "20819636",
    "19557886",
    "964929",
    "6336077",
    "4348647",
    "17940785",
    "3297394",
    "6161636",
    "34660790",
    "10132968"
  ],
  "candidate_category": "book - to-read",
  "source": "goodreads",
  "type": "recommendation",
  "loc": [
    -1,
    -1
  ]
}