{
  "user_id": "33ef6726ca00a507c4c797f981ca8ddd",
  "candidate_list": [
    "16146032",
    "4477907",
    "2869086",
    "16087038",
    "13638490",
    "24509162",
    "6832320",
    "6951328",
    "1306548",
    "856173",
    "17390615",
    "5965951",
    "1460980",
    "7147087",
    "7695797",
    "27207532",
    "777039",
    "28097465",
    "9797404",
    "9008461"
  ],
  "candidate_category": "book - to-read",
  "source": "goodreads",
  "type": "recommendation",
  "loc": [
    -1,
    -1
  ]
}