{
  "user_id": "7d1f4ab9783eb4c18a076f6ae3572ce0",
  "candidate_list": [
    "89562",
    "1999242",
    "1108012",
    "20256396",
    "20759585",
    "12199470",
    "24826528",
    "29790568",
    "35972541",
    "133647",
    "9620343",
    "20257476",
    "3212755",
    "3917912",
    "6051888",
    "271248",
    "6779908",
    "15704307",
    "17445469",
    "107748"
  ],
  "candidate_category": "book - to-read",
  "source": "goodreads",
  "type": "recommendation",
  "loc": [
    -1,
    -1
  ]
}