{
  "user_id": "98b3b569663dda7c9e0d9c358da21a2f",
  "candidate_list": [
    "17277799",
    "5958678",
    "23514087",
    "659648",
    "53492",
    "11149292",
    "3111506",
    "3556293",
    "26064724",
    "21088019",
    "17910168",
    "23438133",
    "5849461",
    "7717911",
    "2326424",
    "6391300",
    "397812",
    "9311930",
    "10201411",
    "15926774"
  ],
  "candidate_category": "book - to-read",
  "source": "goodreads",
  "type": "recommendation",
  "loc": [
    -1,
    -1
  ]
}