{
  "user_id": "lYtxh-L5yvp41FYXL2r4-A",
  "candidate_list": [
    "SRSHXW5urzw4UYZNY3Zzdg",
    "uId0C57ap-5dEJJyEsNu9w",
    "Lpi6YPDrQgpe6ej-o__wNQ",
    "pEa6tpYyl2NDOPfY1OfFyQ",
    "rWn5btW4MA4ep9y4aLTJrg",
    "UUN0qEgDXd_vQecEbRPtGQ",
    "blmEheu3d9tjZ5PPDdrFCQ",
    "tkyHFPJ3dBsjE2hA_tk_sQ",
    "L4q1Zt0yQ7w3CbpH8ED_Dg",
    "KLhihQ0r0BYD9ySP-WMT9A",
    "cvwYlbvxGOtNNNds_r409w",
    "mlrzM-jUkKot28XJhScuuA",
    "mKlgBPF6TSuy3usq7hG1ew",
    "2YyIIdwnYv5cApn1gZo_gw",
    "wsD5oy7YMFB1EEzYrSUS1Q",
    "xHrDP1y4H-aCUtKKcjyWRQ",
    "vhDWGF-8BfsxvS7Zo5Wv2w",
    "ShYwqkUf7PkI7LHqCyTmEA",
    "NitglJNDVoAM_Wr5q_mM7w",
    "1MSqiroAeu3ZeOWjtls8Dg"
  ],
  "candidate_category": "business - Beer, Wine & Spirits, Nightlife, Food, Beer Bar, Bars, Restaurants, Modern European",
  "source": "yelp",
  "type": "recommendation",
  "loc": [
    -1,
    -1
  ]
}