{
  "user_id": "ZG5Ye9RVVCBSL0tVjGLqGw",
  "candidate_list": [
    "cIONZAM2FvxsDfE97dgRtw",
    "kTUKF25sGzCFadFV_OehLA",
    "-YZ1R9bhOjJaqrsfH0GZGQ",
    "BxfvdHqETU8jWYUjx5OL2A",
    "tcDpEgmd14W4szC0DU3Pgg",
    "EjX5CZJ_2vype0z1iP0zGQ",
    "yQ1Htlu3TRT6HMGFt-JEPg",
    "W1ljzP3RA2vjQ8R0HXshZw",
    "sMEsG9hzLSuxedG_MVR9OQ",
    "55uWj7Gv6_KrQNWZCHQAug",
    "bJFVF1wnQscEbOuEZ7aJwQ",
    "JlKaAWO7yHAJXWGcMQ3ZYA",
    "t3HpsSsT3F-c42lCmGxeJw",
    "8IVi6Yjmlh5woIusg0OHUg",
    "7mlVa9-CgYL_M6moJXLCfQ",
    "QHWYlmVbLC3K6eglWoHVvA",
    "hRGO29QsdM9fksSuOMvS9A",
    "O1loDUXiJw4IPYk1DR3pSQ",
    "n2MMGm0z7bfYIlvOKv6XZg",
    "XSifFtuHFYS8I1aRleNUPA"
  ],
  "candidate_category": "business - Burgers, Bars, Restaurants, American (Traditional), Vegan, Asian Fusion, Cocktail Bars, Breakfast & Brunch, Soul Food, Sandwiches, American (New), Gastropubs, Comfort Food, Nightlife, Wine Bars, Delis",
  "source": "yelp",
  "type": "recommendation",
  "loc": [
    -1,
    -1
  ]
}