{
  "user_id": "8GFGiIOqhpJhxxgwUmHcXg",
  "candidate_list": [
    "xoVTtQd6xRrFbQcdfH0dLA",
    "t40e1Vl7vEfWEobf1DxRhg",
    "bPoU-QnlvgbTZWqsENpKpQ",
    "zu8Q3zYfgJaOn96LbPt_Hw",
    "BbwN6GeKWxvgWaqXdFWokw",
    "8Mzu_wczdzv9dU_Gr6OR8A",
    "PG9vb6SXpm0a3UBlUqPWTg",
    "ixj7fzkBZOvwIphmfbyJMg",
    "Nsr46P7bRd1lATqE7H09Pw",
    "EiwbnjJzn4KQ1hkZORn4fg",
    "I1zOgA7Ee57snA2im7QiDg",
    "rZKj0nd_DZR5yqxsTgzQ0Q",
    "bEn-Im7R7Ic4XDORq6_oSQ",
    "Ue1s07RYxb6IDIwZ8sq0Sg",
    "_msFUghqBbYNmO8grFJNAQ",
    "dMOv-lIQ9-2TGOfuAyzgOg",
    "c6uQt1YDKKhAtIA4_rFVCw",
    "qkZuRx-jaEGnRb3tvzGspQ",
    "EfpQ1gPf4GjXs31MyrFWAg",
    "UjWP0znWu3HzqZiHRt2qZg"
  ],
  "candidate_category": "business - Food, Ice Cream & Frozen Yogurt, Juice Bars & Smoothies, Gelato",
  "source": "yelp",
  "type": "recommendation",
  "loc": [
    -1,
    -1
  ]
}