{
  "user_id": "TLfzOj3sO1KS_582UXLiVw",
  "candidate_list": [
    "SPqvspwLv7dOWF6TTm01aQ",
    "ZJGo8ch9AGkl63hdbgeEkA",
    "4EDFnzdMBdrL4tujAA2QZQ",
    "C-JAsI-tgmf_eRmMXTp9Ew",
    "_EkKoNEH0uIZ-h9kWjdhVQ",
    "VnFIoBEiuUdS8mAMbULpGQ",
    "_7b9HAH2lJoeLfHTldZ9hA",
    "krTHKI0YOpASr4gz2CVWFw",
    "3pBYcS2co6J8ixnWZyKyJw",
    "ZiWPJfcHiR28sVhf5K6P0w",
    "TyYpzJzeKWtyMdPFtPRUEg",
    "wSBOPm5hzdhvRsgIHxraJw",
    "AOKfdsiBNABpvW9p78VNmg",
    "Iug9524c_q3EPl-IZLLLRA",
    "ciLydXHeKxmvSsYMc4StUw",
    "BhxXl_vBhnYWeVPcf8a9uQ",
    "bCIZeggW02uPdz2lobSjUA",
    "J9Bc1bZuxGo2VtAo-txgRA",
    "iOBs_J9oVIwVKsmfBHBs6w",
    "OVbuOxR3zXExZCKLXewaVg"
  ],
  "candidate_category": "business - Coffee & Tea, Restaurants, Food, Bars, Nightlife, American (New), Beer Bar, Coffee Roasteries",
  "source": "yelp",
  "type": "recommendation",
  "loc": [
    -1,
    -1
  ]
}