{
  "user_id": "Up-AT0u-BiFDJDMFlxu-Pw",
  "candidate_list": [
    "vGc7Ej5_5rKBHjqiPORE4g",
    "yeg7yNRa84BQqfTW4XX_qg",
    "yi8w-wG4qmISbuad2ItGlQ",
    "AZ5sk4X3LQ5BNLxeGPaddw",
    "450dgxdtJSHfeMbwAurhCw",
    "BcsRUZAeUiU6LSj7Ovtwxw",
    "iVNGTZnc9RWf_i2iCsuNIA",
    "zoLDiSRbOtAd2bY0ehn6uA",
    "OCMrwo6MPIQBeUKwfn0iDg",
    "moCsUKON8hda7f8rnRXHLA",
    "JqreEdoDaC-yR9bOfrezSA",
    "EvDZxSv_9UlAOH1NyKzb8Q",
    "FGe8_MFciERzA_sM7FNJNA",
    "bAJpm0EfWkxJSuKlhQHRQA",
    "qy1pjoe6uuESf7kmLvFqzA",
    "DvBdqAA3XleMaOMwBl7g4g",
    "gj0EbxvhqkgtOirPfVcfIw",
    "yi4nsMJI0U_ERjg6QxEx5Q",
    "R9ChdrBNTZb-pW3yL9BG_g",
    "DVhjFN8N-jpw_EC_-Uoxjg"
  ],
  "candidate_category": "business - Arts & Entertainment, Art Supplies, Art Classes, Nightlife, Art Galleries, Paint & Sip, Education, Event Planning & Services, Shopping, Party & Event Planning, Arts & Crafts",
  "source": "yelp",
  "type": "recommendation",
  "loc": [
    -1,
    -1
  ]
}