{
  "user_id": "NeHob7fIx06Npl2lQBE9Qg",
  "candidate_list": [
    "Hhz99HuzUS2XSwsDOyTmFA",
    "FI4pb2c5CizlSdj6PI-_Ew",
    "xF-G-MZCfZdFIA9bSUSZdA",
    "LpuMOJG8A8g_2ECFsrSwrw",
    "zDKUZcAuCPPeBEbCQ-jmsg",
    "fWMdHjV4G6z8jFW-hf-mIw",
    "4nJ1L8QMKujkh8_Oe4FK6A",
    "srAsUlj4eh0SaxMJY0STmA",
    "EMp87GsYkVdwHftE7Ar2_w",
    "bTYddYIt-e1ls4Hlv5areA",
    "7xR0yUaF1cmQdJZlPVIENA",
    "4kTeF5mHEkXzO-q1sxHZ2A",
    "WhD9lOd_Dj9WAprIHzAIHA",
    "PmVnSdu4G0BN-ykRpjX7uQ",
    "IW19SVvxiuRlSt3QQmx2OQ",
    "sDUNW9dXc92gQlHKgT_WgA",
    "f_CBREzIBnIES0hejwSwOQ",
    "Itft7SwYFUXP02MpcijMOQ",
    "7Oeim4OvpZRkIc2w59Lubw",
    "RnqU698MbIjq_eZHEzYL6g"
  ],
  "candidate_category": "business - Restaurants, Coffee Roasteries, Cafes, Coffee & Tea, Food",
  "source": "yelp",
  "type": "recommendation",
  "loc": [
    -1,
    -1
  ]
}