{
  "user_id": "FCV8BrR2igjy29bUHLbTpA",
  "candidate_list": [
    "8DVTsGSLW0bElAnktnPK4A",
    "PBVd6ibsenSrHJScf98o5Q",
    "8j5bQ0nDwoGiFaTQDNCQTg",
    "TPl-ZIXCP4yBA_OygHCbNQ",
    "Ft2EWgzl9wPBwNBjBevEjg",
    "MqAvonk4-cJ-7pW78tR1Rw",
    "c2zfvdiLqExtrHGRJahmTQ",
    "Jg9kkOl4sx2AXJVohbpSiw",
    "PTLrCyt89PsIrsqd85ttBg",
    "BZyxr4ocl1hJvFvhlogz0Q",
    "paoYG3VEjW5OwVXVbQobJw",
    "0v0OzOuhxmtmv2-SRWJYjQ",
    "PvT44WlqJLkUrCITo6AjRA",
    "pXQzeEk90WRdHSMoIVZ9HA",
    "q4sI8dkd3QaGQ4qY-GQa2A",
    "D9lnOVIpb-0F9DfcQN_rgw",
    "rX4pmubWdgrKEG794iwbWA",
    "OIGWeqqmbLUkbs2GmJSuvA",
    "k7QlQlt3ezxu_87x26MvxA",
    "VXtQVIYWNcLlNJxGA7cDkg"
  ],
  "candidate_category": "business - Sandwiches, Vegetarian, Delis, Cafes, Restaurants, Breakfast & Brunch, Cuban, Salad, Food, Desserts",
  "source": "yelp",
  "type": "recommendation",
  "loc": [
    -1,
    -1
  ]
}