{
  "user_id": "Kl8Ei6zu8lsXKJ0tffXPWw",
  "candidate_list": [
    "yHDaRDsyYXcT8_n0dcc49w",
    "o6Om36i4Hq7hMAW5dnJquA",
    "zZ01WQlcpI1_n806WKV3bA",
    "HJSY4FQViwzHnTF7d-IUdQ",
    "4uF4fXn7fJkvpzixZdF0bQ",
    "tu_y0SVk9w3rWcAM2ebqng",
    "s2GPXV30E17juvBRpv3YGw",
    "y7IbpgftK97lerMOrgHFoA",
    "0g9fM6LZ036UxN93HosX1A",
    "DjpCcVUuolhT6FF78W1aQw",
    "OFSrGC3hrP3SvZcernZl8Q",
    "rOYVkIqBDQ-shKwUhJp7gw",
    "WANyiYJgedwrNuV63x8s1g",
    "nqMGXZ3haILky26NDAJVSA",
    "grwQ0HSdvZBSUPzHCijk6Q",
    "Kya7-ov8E4a6UiP5EbuO9w",
    "iuXreIw6khsp6MH7lEOQJQ",
    "24AvZmbQOjUzmpH1TOuDGA",
    "iSOwZtXQaUBf5tX-MTVT4w",
    "l0yZbDB4P7vh0wm_4R_CvQ"
  ],
  "candidate_category": "business - Restaurants, American (New)",
  "source": "yelp",
  "type": "recommendation",
  "loc": [
    -1,
    -1
  ]
}