{
  "user_id": "UAhnm7zPhL35GWNnB5IcAQ",
  "candidate_list": [
    "BK6In_HrWgAYZjQLTdbg0Q",
    "rpKsCkLKypkHsuwPyxPwKw",
    "zxY4DgtXsVHihSUpsmwamg",
    "iPp4qATdAC6UbujaCwjhNA",
    "d7TWHwAS6q60OWMf-0SPdQ",
    "_tADqh3OmH6CzGJWKkru3g",
    "qZSCVXwt6ToIUr0TMDTskA",
    "nRGxU90L9oTr2YUSPNakKA",
    "wYYsmF6begc6ZcnPGwF9NQ",
    "EWs93-O_zF1mpGVZka2Tdw",
    "JPDIx15s02mN2eYyO4BBQQ",
    "1Sk3-T3lQPDsmLEHMCUZHQ",
    "QMSevKu2-czkn3KjkvQOsw",
    "45WLhjZ42-_WL1FcDXErsQ",
    "pX79hg6t0WsaCzU2npdK5w",
    "THS40i9JgqPRm6jZf7Kmeg",
    "LjgiE_EbpBdIz4JyVUioTQ",
    "WZUIlyefoUhuH_VkVCEyAw",
    "-k0SQn1uQVn0FN61uXYMsw",
    "eAvshvKv5PaUTS3jQROGkA"
  ],
  "candidate_category": "business - Italian, Restaurants, Venues & Event Spaces, American (New), Nightlife, Cocktail Bars, Bars, Pizza, Event Planning & Services",
  "source": "yelp",
  "type": "recommendation",
  "loc": [
    -1,
    -1
  ]
}