{
  "user_id": "Ysz_q1iEFLVBLfaziOC2gg",
  "candidate_list": [
    "cdrMvOVFFBSwYHb3s06U9w",
    "x8joRxn_TPorP1C2LSdSYg",
    "3IjpO8tHrDkltcshN_m-7g",
    "YrHkfX3Rngx4ZTR04wb9bA",
    "7Ktwb4zuXdwodsA3UPuO5A",
    "pXQzeEk90WRdHSMoIVZ9HA",
    "9ogKOflx0n1emRfRu2hJMQ",
    "9fp70Eh-nSZ9ANzh8fFQPA",
    "-y9SJ2UBHqcekg7AnvGOpA",
    "jU_3btpjDnE7gp8fVwJ2jg",
    "6njow-DCdwWjA3fMHCSo0w",
    "-xtnwq4VBA2XFobjDGz0Ww",
    "JJ6tYuw5Ms_r58DhnMtOCA",
    "gM9GAwQUJxGXzmSHuJUF1w",
    "5sGryBnSx35jx7rBbr_DnQ",
    "TgZ1lEX3jPENYHNhMpDBxw",
    "5Apcp9iRdnIG__iXIEnILA",
    "7h7LKtSIy6Vac6CmjbK6Pw",
    "ds60IfUbhaQCPKpQhVITtA",
    "yyTuqf5DIJG0NAWnwMQiWg"
  ],
  "candidate_category": "business - Nightlife, Food, Event Planning & Services, Coffee & Tea, Bars, Party & Event Planning, Hookah Bars",
  "source": "yelp",
  "type": "recommendation",
  "loc": [
    -1,
    -1
  ]
}