{
  "user_id": "_qDBBoXEGB5AdRb33uJrNA",
  "candidate_list": [
    "DNMdZVVfhus2H-dH0mI3HA",
    "NoZgfiWSD0hy6knY44SfbA",
    "BLdx9HaexMj6UXnGNaD9hA",
    "40xoTPjCQ9uvpc2GqGnEqA",
    "phVGUNqxTMnbE7yie3grfw",
    "QFwWERpeo3kESm-wX0j2kw",
    "k_CZOE7EDy3aE-LqzB3CXg",
    "HnZCbSY0Ipn8Ydg0Ii8xCg",
    "zBWbOVWOXcytve2sYm1HvA",
    "402dEWTSI6Nxg15oRJ7znQ",
    "j5fzB-R9kbynYUEFiw8Bkg",
    "uKKRHbXXAIuGxOxs9miwOg",
    "G93MrbfqrR5vGtGDxqujHw",
    "G5bm_MBXXkX4TwVPtke7-w",
    "L68ofRH1fVUwYPCAVgVKCA",
    "gB9c_OMjvGrn36XjHArAUQ",
    "u-q5PIRns-cMvzL4fntlZA",
    "aI58hxqbyOX6irFfljXfQA",
    "izo9vZ7oFb6c5eC6cBiACA",
    "RG0j0euUZJobcEBoHPhPJA"
  ],
  "candidate_category": "business - Pubs, Food, Breweries, Nightlife, Bars, American (Traditional), Sports Bars, Restaurants, American (New)",
  "source": "yelp",
  "type": "recommendation",
  "loc": [
    -1,
    -1
  ]
}