{
  "user_id": "isZ2BuPrsliCz6juDgjrmw",
  "candidate_list": [
    "ih3AO3uheAMbTzrzvxlgQg",
    "PBvzv2e1Y_Rn5uSQ6Miovw",
    "DkH8wLb_aIKz6oICawbFhw",
    "Wl-uaUetFGDjT9a3-6Z3pw",
    "TFX-oYY3SZLmuUJwUkZXLw",
    "xcQy8NRwrKao8MovWchEeA",
    "sUr-aMrvtMrj07tW5JcpeQ",
    "TvEYDf_w7ednlvmYMA6PbA",
    "9iDHCh_a3q9KStftkzHlZA",
    "wqohggEOO8Ul4GMWQmIW4Q",
    "aZOV4YdjgZgs5cRRt_FAWg",
    "r43WSb-owICp-X8vAN8g5g",
    "408J0FMClRAstxyrt9wXEQ",
    "KyPRB9TtrHfZFhMv0yDkUA",
    "jbIHN6TuseNIqhzzv67aLw",
    "Xcbl8kRa45Bb2tkvHSXd3Q",
    "zKcb2vGceLnwiCKeC9qF0g",
    "n9YO7U3bbudSwIpkCtQZiA",
    "TLT604auMwiH18EKh4J-aQ",
    "zQVAO6s0zeUk44UzTcJj_g"
  ],
  "candidate_category": "business - Bars, Seafood, Cocktail Bars, Live/Raw Food, Nightlife, Restaurants",
  "source": "yelp",
  "type": "recommendation",
  "loc": [
    -1,
    -1
  ]
}