{
  "user_id": "eGbqHKB8K-Ho1ycLKDHVag",
  "candidate_list": [
    "nKwlg5V7tmNyYP-BDrDu2w",
    "KxrXqdsgT7lcghhNk00z6w",
    "Lf3Wy8iD3mMoj-sOqWTT3w",
    "JIcWbxkBJoDtoZgVu2_pxQ",
    "gPr1io7ks0Eo3FDsnDTYfg",
    "O6Mn8SQzavRYCOiVeuZ6Jw",
    "1wrdcb_Rw586DBZnfSNGkQ",
    "XHvzvwJ5IaB3WtFjsEswtw",
    "GZDUQ9P8oNRa8E3hJWXgmw",
    "l7e7-RIhNx-kiZ9hQo6iLg",
    "tdt-kHYKKigMWGGN6ynV2A",
    "hrAd9yxS_hsSqeAhOBeQwQ",
    "RadvqFuRTZNEfSZ_avPRog",
    "vej-CJsldyvpUOdb7oKYeA",
    "oLSD2gqZ6_LANC85f1C3Bg",
    "quDVZ59BPp3Ze5F4uOd3Ww",
    "3LcxYHWulzue7Um9q_FK5g",
    "GduRGjJmz2syYgaL83RInw",
    "BNqtMJ-zXdHn49eaegGumg",
    "fJQzUesrvvoMUkjQBNxc6g"
  ],
  "candidate_category": "business - Tex-Mex, Tacos, Vegan, Restaurants, Mexican, Breakfast & Brunch",
  "source": "yelp",
  "type": "recommendation",
  "loc": [
    -1,
    -1
  ]
}