{
  "user_id": "DihTsliUxbqpoA9W3uRDBA",
  "candidate_list": [
    "1BZcRoLmJ55rDM5rgt4nLA",
    "JfY3JGa4Vd9nd38TIP8Adw",
    "Nd5_2zQ1SQuNd8UbBOFKQw",
    "qI3ljJxraYSzMqHVVU5jPg",
    "JtR478zXy-jJn0tbGUn7yQ",
    "hyrITbzxrU9WmVjstt9MwA",
    "JlbAYc0fgqVX2IVT113BnQ",
    "e5zr_YpVmrnZsF_9CX81KA",
    "Wox7ip8nWsnUb3k53X8vyw",
    "eStBQLShT60Z5C3e1BjAOw",
    "6GeezpXz_jYeVnt450fOKg",
    "7X7Zp3fOwRzOgswiL6NIcQ",
    "TEeVMT8UQYMHwnN81ANY_A",
    "gkrDiCU_sRZKwuBlhEzv6A",
    "hMV0U7zpIFVgPQU5fiS2rA",
    "7akaRRko9CzFQ3FGemCn4g",
    "o46yygtcv5vOQShnEnfNpQ",
    "8InvOBDq-jeVpsp-T8Wtng",
    "VfTArv5LYZyF25csBMUJVg",
    "6geIGIYJc8-3wZHxJCJBNA"
  ],
  "candidate_category": "business - Japanese, Restaurants, Sushi Bars",
  "source": "yelp",
  "type": "recommendation",
  "loc": [
    -1,
    -1
  ]
}