{
  "user_id": "o7iIo8j2iWML_zp3E_7-bQ",
  "candidate_list": [
    "5Ou75rsQZMtr2MINech6gw",
    "DCkboujFVLvFiAQ2qnBWig",
    "CVK8ENkVyoxfIHdrupIc2A",
    "FJaTierDJxsT8XxCrrfCug",
    "GMjmrbksSxabPHYmhjsOEw",
    "liPt8EZuHzf31IBLpZnhMA",
    "BtysWNfk4eGUNbFcyvVOHA",
    "2JhpJoS6Md9pqCxD5Uubhg",
    "-rBLDkfHNXV8LzofwLcjHw",
    "o6veeboEXZWzliK3EmL5ig",
    "mL5NrbO6lxHUeBrWtou5VQ",
    "tSRICEpYkNZyeCyHYMsM7w",
    "0WX9lNZPC_w0oaq8pvBr4w",
    "SsO-upa1JJI2OfbcsHLWmA",
    "VZPqQGDDGRwKFG79eP-ZjQ",
    "DlOZoZZRLEOuh9FdAw1few",
    "SLbJHaNqY3wcRaO6L21aZg",
    "qUHOwXHHY1zj44t9Ap00Uw",
    "Omct7HvsAFeWgfTT0ctEtA",
    "RnhLCG4N9MPy6ZRzq787Cg"
  ],
  "candidate_category": "business - Hair Salons, Men's Hair Salons, Barbers, Beauty & Spas",
  "source": "yelp",
  "type": "recommendation",
  "loc": [
    -1,
    -1
  ]
}