{
  "user_id": "jJPU8dEMJ2xKXYN2sExviQ",
  "candidate_list": [
    "y5aRZEQExOFZwJ2Hj8htbw",
    "WzfLerGWxtb6j4xvUBrQwA",
    "iJfAoWtETn-F8WjC4g_hgw",
    "Us3IgZ-egSAAxIHKhbP0Ug",
    "8k3IvUeYZOf5XdM4VslcKg",
    "enXvNN8pFfz76KT1PZFlPQ",
    "dGyW8a78NJfwQZVllZ98wA",
    "RlJLO-WXW7IP-LSSdvqWJA",
    "LtH43ufxtYgdNi8LgtpfMg",
    "rQW9iupvhk6ScPn2VPNLVQ",
    "08Tevbnf5sSmfHtSIjXJBg",
    "y1C5nw1WcrojI5JFZxK9bw",
    "3TagDMAD_Ciy0_Sg3kJf2w",
    "rJNdserUMHaxq_kkJ8Ga3Q",
    "6XiTlNnstoTK3tUPkc0Gbw",
    "LUs6ltKjOl23WpEpHA3NQA",
    "iksVwRfpWymIUUFqw0tXpw",
    "vDUPgJdR2Ro1aRE5PXyCjw",
    "7E3mhfqDUSe0oKaZ9VikGg",
    "Eynpakzpkx5i5oFarjaMVg"
  ],
  "candidate_category": "business - Chicken Wings, Restaurants, Burgers, Sandwiches, Cheesesteaks, Steakhouses",
  "source": "yelp",
  "type": "recommendation",
  "loc": [
    -1,
    -1
  ]
}